web_watchr/__init__.py
web_watchr/watchr.py
web_watchr/alert/__init__.py
web_watchr/alert/abstract_alerter.py
web_watchr/alert/print_alerter.py
web_watchr/alert/telegram_alerter.py
web_watchr/compare/__init__.py
web_watchr/compare/abstract_comparer.py
web_watchr/compare/dummy_comparer.py
web_watchr/compare/fs_comparer.py
web_watchr-0.7.0.dist-info/METADATA
web_watchr-0.7.0.dist-info/WHEEL
web_watchr-0.7.0.dist-info/licenses/LICENSE
web_watchr-0.7.0.dist-info/RECORD
