Metadata-Version: 2.4
Name: web_watchr
Version: 0.7.0
Summary: Monitors a website for changes in a text element and publishes an alert (e.g., on telegram)
Project-URL: Homepage, https://github.com/Emrys-Merlin/web_watchr
Project-URL: Documentation, https://Emrys-Merlin.github.io/web_watchr/
Project-URL: Repository, https://github.com/Emrys-Merlin/web_watchr.git
Project-URL: Bug Tracker, https://github.com/Emrys-Merlin/web_watchr/issues
Author-email: Tim Adler <tim+github@emrys-merlin.de>
License: MIT
License-File: LICENSE
Keywords: bot,scraping,telegram
Classifier: Development Status :: 3 - Alpha
Classifier: Intended Audience :: Developers
Classifier: License :: OSI Approved :: MIT License
Classifier: Programming Language :: Python :: 3
Classifier: Programming Language :: Python :: 3.10
Classifier: Programming Language :: Python :: 3.11
Classifier: Programming Language :: Python :: 3.12
Classifier: Programming Language :: Python :: 3.13
Requires-Python: >=3.10
Requires-Dist: loguru==0.7.3
Requires-Dist: playwright==1.53.0
Requires-Dist: pydantic==2.11.7
Requires-Dist: python-telegram-bot==22.2
